[
    {
        "TAGNAME": "ws2019"
    },
    {
        "TITLE": "停引",
        "FULLNAME": "wanderers:turn-off-gravity",
        "RATING": 3,
        "COMMENTS": "2",
        "TAGS": [
            "wanderers",
            "ws2019",
            "敘述",
            "翻譯",
            "記載"
        ]
    },
    {
        "TITLE": "星際廣播頻道5號",
        "FULLNAME": "wanderers:interstellar-radio-channel-5",
        "RATING": 7,
        "COMMENTS": "0",
        "TAGS": [
            "entry",
            "prose",
            "wanderers",
            "ws2019",
            "翻譯"
        ]
    }
]