[
    {
        "TAGNAME": "飾品"
    },
    {
        "TITLE": "SCP-ZH-940 - 獵巫",
        "FULLNAME": "scp-zh-940",
        "RATING": 7,
        "COMMENTS": "4",
        "TAGS": [
            "safe",
            "scp",
            "site-zh-16",
            "原創",
            "張道士",
            "繁廣",
            "藝術性",
            "飾品"
        ]
    },
    {
        "TITLE": "SCP-ZH-030 - 紅色浪潮",
        "FULLNAME": "scp-zh-030",
        "RATING": 7,
        "COMMENTS": "0",
        "TAGS": [
            "safe",
            "scp",
            "site-zh-16",
            "原創",
            "幻覺",
            "強迫性",
            "死亡永生",
            "精神影響",
            "聽覺影響",
            "認知危害",
            "飾品"
        ]
    },
    {
        "TITLE": "SCP-ZH-095 - 守護, 愛, 祝福",
        "FULLNAME": "scp-zh-095",
        "RATING": 11,
        "COMMENTS": "0",
        "TAGS": [
            "safe",
            "scp",
            "x博士",
            "不可摧毀",
            "共感",
            "原創",
            "死亡永生",
            "精神影響",
            "聲音",
            "認知危害",
            "飾品"
        ]
    },
    {
        "TITLE": "SCP-ZH-747 - 趨凶避凶",
        "FULLNAME": "scp-zh-747",
        "RATING": 15,
        "COMMENTS": "1",
        "TAGS": [
            "euclid",
            "scp",
            "site-zh-01",
            "原創",
            "普羅米修斯實驗室",
            "智能",
            "本質促動",
            "死亡永生",
            "精神影響",
            "視覺性",
            "認知危害",
            "金屬",
            "飾品"
        ]
    },
    {
        "TITLE": "SCP-ZH-085 - 守護之鍊",
        "FULLNAME": "scp-zh-085",
        "RATING": 6,
        "COMMENTS": "5",
        "TAGS": [
            "2020虹光之間",
            "meta",
            "safe",
            "scp",
            "原創",
            "宗教",
            "飾品"
        ]
    },
    {
        "TITLE": "SCP-ZH-960 - 奪舍玉珮",
        "FULLNAME": "scp-zh-960",
        "RATING": 5,
        "COMMENTS": "0",
        "TAGS": [
            "2020夏季競賽",
            "2020攀爬金字塔",
            "scp",
            "site-zh-16",
            "原創",
            "木易",
            "無效化",
            "精神影響",
            "銘文",
            "飾品"
        ]
    },
    {
        "TITLE": "SCP-ZH-327 - 花兒與檳榔",
        "FULLNAME": "scp-zh-327",
        "RATING": 12,
        "COMMENTS": "3",
        "TAGS": [
            "safe",
            "scp",
            "site-zh-44",
            "人造物品",
            "傳染性",
            "共感",
            "原創",
            "反熵",
            "台灣原住民",
            "容器",
            "幻覺",
            "生物性",
            "知識",
            "神異博覽會",
            "聽覺影響",
            "記憶影響",
            "飾品"
        ]
    }
]