[
    {
        "TITLE": "SCP-ZH-818 - 博十八豆仔",
        "RATING": 10,
        "FULLNAME": "scp-zh-818"
    },
    {
        "TITLE": "SCP-ZH-744 - 反洗禮",
        "RATING": 13,
        "FULLNAME": "scp-zh-744"
    },
    {
        "TITLE": "SCP-ZH-196 - 與ㅤㅤㅤㅤ婆娑起舞",
        "RATING": 17,
        "FULLNAME": "scp-zh-196"
    },
    {
        "TITLE": "SCP-ZH-002-J - 水推車",
        "RATING": 14,
        "FULLNAME": "scp-zh-002-j"
    },
    {
        "TITLE": "NX-ZH-02：西加走灣群島",
        "RATING": 21,
        "FULLNAME": "nx-zh-02"
    },
    {
        "TITLE": "SCP-ZH-403 - 禁臠與終止符",
        "RATING": 14,
        "FULLNAME": "scp-zh-403"
    },
    {
        "TITLE": "SCP-ZH-587-J",
        "RATING": 22,
        "FULLNAME": "scp-zh-587-j"
    },
    {
        "TITLE": "SCP-ZH-105 - 不孝子",
        "RATING": 65,
        "FULLNAME": "scp-zh-105"
    },
    {
        "TITLE": "SCP-ZH-051",
        "RATING": 15,
        "FULLNAME": "scp-zh-051"
    },
    {
        "TITLE": "SCP-ZH-2005-EX",
        "RATING": 55,
        "FULLNAME": "scp-zh-2005-ex"
    },
    {
        "TITLE": "SCP-ZH-416",
        "RATING": 8,
        "FULLNAME": "scp-zh-416"
    },
    {
        "TITLE": "SCP-ZH-037",
        "RATING": 20,
        "FULLNAME": "scp-zh-037"
    },
    {
        "TITLE": "機動特遣隊擴充系統：黃道二十八宿",
        "RATING": 8,
        "FULLNAME": "task-forces-zh-28-xiu"
    },
    {
        "TITLE": "SCP-ZH-1000-EX",
        "RATING": 18,
        "FULLNAME": "scp-zh-1000-ex"
    },
    {
        "TITLE": "異常項目紀錄：「防暴警察頭盔」",
        "RATING": 35,
        "FULLNAME": "anomalous-item-hk-police-helmet"
    },
    {
        "TITLE": "引號之間",
        "RATING": 13,
        "FULLNAME": "in-the-quotation"
    },
    {
        "TITLE": "SCP-ZH-279 - 愛的形狀",
        "RATING": 17,
        "FULLNAME": "scp-zh-279"
    },
    {
        "TITLE": "愛是犧牲奉獻",
        "RATING": 6,
        "FULLNAME": "love-is-sacrifice"
    },
    {
        "TITLE": "SCP-ZH-184 - 奔車朽索",
        "RATING": 12,
        "FULLNAME": "scp-zh-184"
    }
]